{
    "home": {
        "title": {
            "EN": "home",
            "VN": "trang chủ"
        }
    },
    "aboutMe": {
        "title": {
            "EN": "About Me",
            "VN": "Giới Thiệu"
        },
        "desc": {
            "title": {
                "EN": "summary",
                "VN": "tổng quát"
            },
            "status": {
                "EN": "looking for work",
                "VN": "đang tìm việc"
            },
            "greeting": {
                "EN": "hi. i'm",
                "VN": "xin chào, tôi là"
            },
            "myName": {
                "EN": "ho thai khanh",
                "VN": "hồ thái khanh"
            },
            "jobTitle": {
                "EN": "fresher frontend developer",
                "VN": "fresher frontend developer"
            },
            "content": {
                "EN": "A Passion for programming and a love for problem-solving. With over 4 years of experience in developing, delivering product while working, collaborating in a team. Open-minded and ready to adapt to new technologies while self-motivated and determined to deliver the product at the highest quality with great attention to detail and within the desired time limit.",
                "VN": "Là một người đam mê lập trình và yêu thích giải quyết vấn đề. Với hơn 4 năm kinh nghiệm trong việc sản xuất, phát triển sản phẩm và làm việc, phối hợp trong một nhóm. Cởi mở và sẵn sàng học học hỏi các công nghệ mới, đồng thời chủ động và quyết tâm để có thể bàn giao với sẩn phẩm với sự tỉ mỉ và chất lượng tốt nhất trong khoảng thời gian đã định trước"
            }
        },
        "downloadBtn": {
            "EN": "download cv",
            "VN": "tải xuống cv"
        },
        "skills": {
            "title": {
                "EN": "skills",
                "VN": "công nghệ"
            }
        },
        "relatedSkills": {
            "title": {
                "EN": "related skills",
                "VN": "kỹ năng khác"
            },
            "list": [
                {
                    "name": "EN",
                    "title": {
                        "EN": "English",
                        "VN": "tiếng anh"
                    },
                    "content": {
                        "EN": [
                            "950 Toeic score",
                            "Strong Comminication skills",
                            "Proficient at reading technical documents",
                            "Capable of translating documents from English to vietnamese"
                        ],
                        "VN": [
                            "Chứng chỉ Toeic 950",
                            "Giao tiếp thành thạo",
                            "Dễ dàng đọc hiểu tài liệu",
                            "Có kinh nghiệm biên dịch tài liệu từ tiếng Anh sang tiếng Việt"
                        ]
                    }
                },
                {
                    "name": "GD",
                    "title": {
                        "EN": "graphic design",
                        "VN": "thiết kế đồ họa"
                    },
                    "content": {
                        "EN": [
                            "Experienced with making 2D vector based graphics",
                            "Proficient at Powerpoint and Illustrator"
                        ],
                        "VN": [
                            "Thiết kế ấn phẩm, đồ họa 2D",
                            "Thành thạo Powerpoint, Illustrator"
                        ]
                    }
                },
                {
                    "name": "VE",
                    "title": {
                        "EN": "video editing",
                        "VN": "chỉnh sửa video"
                    },
                    "content": {
                        "EN": [
                            "Proficient with After Effects, Premiere ",
                            "Experienced with video editing",
                            "Capable of making short 2D animations, motion graphics"
                        ],
                        "VN": [
                            "Thành thạo với After Effects, Premiere",
                            "Có kinh nghiệm chỉnh sửa, edit video",
                            "Có thể tạo, dựng video với animation 2D ngắn"
                        ]
                    }
                }
            ]
        }
    },
    "workHistory": {
        "title": {
            "EN": "Experience",
            "VN": "kinh nghiệm"
        },
        "list": [
            {
                "id": "des",
                "companyName": "digital education solution",
                "startYear": 2018,
                "endYear": 2021,
                "jobTitle": "Instructional Designer",
                "duties": {
                    "title": {
                        "EN": "responsibility",
                        "VN": "công việc"
                    },
                    "content": {
                        "EN": [
                            "line1",
                            "line2"
                        ],
                        "VN": [
                            "dòng 1",
                            "dòng 2"
                        ]
                    }
                },
                "achievement": {
                    "title": {
                        "EN": "achivement",
                        "VN": "thành tựu"
                    },
                    "content": {
                        "EN": [
                            "line1",
                            "line2"
                        ],
                        "VN": [
                            "dòng 1",
                            "dòng 2"
                        ]
                    }
                },
                "contact": {
                    "title": {
                        "EN": "contact",
                        "VN": "liên hệ"
                    },
                    "name": {
                        "EN": "name",
                        "VN": "tên"
                    },
                    "jobTitle": {
                        "EN": "manager",
                        "VN": "quản lý"
                    },
                    "mail": "mail@gmail.com"
                }
            },
            {
                "id": "vss",
                "companyName": "viettel software services",
                "startYear": 2021,
                "endYear": 2023,
                "jobTitle": "Instructional Designer",
                "duties": {
                    "title": {
                        "EN": "responsibility",
                        "VN": "công việc"
                    },
                    "content": {
                        "EN": [
                            "line1",
                            "line2"
                        ],
                        "VN": [
                            "dòng 1",
                            "dòng 2"
                        ]
                    }
                },
                "achievement": {
                    "title": {
                        "EN": "achivement",
                        "VN": "thành tựu"
                    },
                    "content": {
                        "EN": [
                            "line1",
                            "line2"
                        ],
                        "VN": [
                            "dòng 1",
                            "dòng 2"
                        ]
                    }
                },
                "contact": {
                    "title": {
                        "EN": "contact",
                        "VN": "liên hệ"
                    },
                    "name": {
                        "EN": "name",
                        "VN": "tên"
                    },
                    "jobTitle": {
                        "EN": "manager",
                        "VN": "quản lý"
                    },
                    "mail": "mail@gmail.com"
                }
            }
        ]
    },
    "projectPages": {
        "title": {
            "EN": "My Projects",
            "VN": "Dự án của tôi"
        }
    },
    "project1": {
        "title": {
            "EN": "Project #1",
            "VN": "Dự án #1"
        },
        "projectName": "Project Name",
        "desc": {
            "EN": "Lorem ipsum, dolor sit amet consectetur adipisicing elit. Sit, magni ullam! Neque doloribus explicabo quaerat voluptatibus nemo sapiente eveniet aspernatur!",
            "VN": "VN, dolor sit amet consectetur adipisicing elit. Sit, magni ullam! Neque doloribus explicabo quaerat voluptatibus nemo sapiente eveniet aspernatur!"
        },
        "techStack": {
            "title": {
                "EN": "tech stack",
                "VN": "tech stack"
            },
            "list": [
                "Javascript",
                "ReactJs"
            ]
        },
        "imageUrl": "/src/assets/img/placeholder.jpg",
        "liveViewUrl": "https://www.google.com/",
        "gitHubUrl": "https://www.google.com/"
    },
    "project2": {
        "title": {
            "EN": "Project #2",
            "VN": "Dự án #2"
        },
        "projectName": "Project Name",
        "desc": {
            "EN": "Lorem ipsum, dolor sit amet consectetur adipisicing elit. Sit, magni ullam! Neque doloribus explicabo quaerat voluptatibus nemo sapiente eveniet aspernatur!",
            "VN": "VN, dolor sit amet consectetur adipisicing elit. Sit, magni ullam! Neque doloribus explicabo quaerat voluptatibus nemo sapiente eveniet aspernatur!"
        },
        "techStack": {
            "title": {
                "EN": "tech stack",
                "VN": "tech stack"
            },
            "list": [
                "Javascript",
                "ReactJs"
            ]
        },
        "imageUrl": "/src/assets/img/placeholder.jpg",
        "liveViewUrl": "https://www.google.com/",
        "gitHubUrl": "https://www.google.com/"
    },
    "project3": {
        "title": {
            "EN": "Project #3",
            "VN": "Dự án #3"
        },
        "projectName": "Project Name",
        "desc": {
            "EN": "Lorem ipsum, dolor sit amet consectetur adipisicing elit. Sit, magni ullam! Neque doloribus explicabo quaerat voluptatibus nemo sapiente eveniet aspernatur!",
            "VN": "VN, dolor sit amet consectetur adipisicing elit. Sit, magni ullam! Neque doloribus explicabo quaerat voluptatibus nemo sapiente eveniet aspernatur!"
        },
        "techStack": {
            "title": {
                "EN": "tech stack",
                "VN": "tech stack"
            },
            "list": [
                "Javascript",
                "ReactJs"
            ]
        },
        "imageUrl": "/src/assets/img/placeholder.jpg",
        "liveViewUrl": "https://www.google.com/",
        "gitHubUrl": "https://www.google.com/"
    },
    "contact": {
        "title": {
            "EN": "Contact",
            "VN": "Liên lạc"
        },
        "header": {
            "EN": "my contacts",
            "VN": "thông tin liên lạc"
        },
        "email": "hothaikhanh@gmail.com",
        "message": {
            "EN": "Lorem ipsum, dolor sit amet consectetur adipisicing elit. Sit, magni ullam! Neque doloribus explicabo quaerat voluptatibus nemo sapiente eveniet aspernatur!",
            "VN": "Lorem ipsum, dolor sit amet consectetur adipisicing elit. Sit, magni ullam! Neque doloribus explicabo quaerat voluptatibus nemo sapiente eveniet aspernatur!"
        },
        "actionBtn": {
            "EN": "",
            "VN": "gửi mail"
        }
    },
    "blank": {
        "message": {
            "EN": "no signal",
            "VN": "không tín hiệu"
        }
    },
    "skills": {
        "path": "/src/assets/icons/tech_logos/",
        "list": [
            {
                "name": "Javascript",
                "icon": "js.svg"
            },
            {
                "name": "ReactJs",
                "icon": "reactjs.svg"
            },
            {
                "name": "NodeJs",
                "icon": "nodejs.svg"
            },
            {
                "name": "Vite",
                "icon": "vite.svg"
            },
            {
                "name": "Express",
                "icon": "express.svg"
            },
            {
                "name": "AngularJs",
                "icon": "angular.svg"
            },
            {
                "name": "Tailwind",
                "icon": "tailwind.svg"
            },
            {
                "name": "Git",
                "icon": "git.svg"
            },
            {
                "name": "ThreeJs",
                "icon": "threejs.svg"
            },
            {
                "name": "Html",
                "icon": "html.svg"
            },
            {
                "name": "CSS",
                "icon": "css.svg"
            },
            {
                "name": "SASS",
                "icon": "sass.svg"
            },
            {
                "name": "Figma",
                "icon": "figma.svg"
            }
        ]
    }
}